circle_of_confusion/__init__.py
circle_of_confusion/_exception.py
circle_of_confusion/_features.py
circle_of_confusion/_ffi.py
circle_of_confusion/_wasm/__init__.py
circle_of_confusion/_wasm/_pywasm.py
circle_of_confusion/_wasm/_wasmtime.py
circle_of_confusion/_wasm/abstract.py
_circle_of_confusion/__init__.py
_circle_of_confusion/circle_of_confusion.wasm
_circle_of_confusion/circle_of_confusion_pb2.py
_circle_of_confusion/circle_of_confusion_pb2.pyi
circle_of_confusion-0.2.7.dist-info/METADATA
circle_of_confusion-0.2.7.dist-info/WHEEL
circle_of_confusion-0.2.7.dist-info/licenses/LICENSE
circle_of_confusion-0.2.7.dist-info/RECORD
