Metadata-Version: 2.4
Name: circle-of-confusion
Version: 0.2.7
Summary: Calculator for Circle of Confusion (CoC) to calculate the size in pixels of an area, used for depth of field processing.
Project-URL: Homepage, https://codeberg.org/gillesvink/circle-of-confusion
Project-URL: Bug Tracker, https://codeberg.org/gillesvink/circle-of-confusion/issues
Project-URL: Changelog, https://codeberg.org/gillesvink/circle-of-confusion/src/branch/main/CHANGELOG.md
Author-email: Gilles Vink <gillesvink@noreply.codeberg.org>
Maintainer-email: Gilles Vink <gillesvink@noreply.codeberg.org>
License-Expression: EUPL-1.2
License-File: LICENSE
Classifier: Environment :: WebAssembly
Classifier: License :: OSI Approved :: European Union Public Licence 1.2 (EUPL 1.2)
Classifier: Operating System :: OS Independent
Classifier: Programming Language :: Python :: 3
Classifier: Programming Language :: Python :: 3.9
Classifier: Programming Language :: Python :: 3.10
Classifier: Programming Language :: Python :: 3.11
Classifier: Programming Language :: Python :: 3.12
Classifier: Programming Language :: Python :: 3.13
Classifier: Programming Language :: Python :: 3.14
Classifier: Programming Language :: Python :: Implementation :: CPython
Classifier: Programming Language :: Python :: Implementation :: MicroPython
Classifier: Programming Language :: Python :: Implementation :: PyPy
Classifier: Programming Language :: Rust
Classifier: Topic :: Multimedia :: Graphics
Classifier: Topic :: Scientific/Engineering
Requires-Python: >=3.9
Requires-Dist: protobuf==6.33.0
Requires-Dist: pywasm>=2.2.1
Provides-Extra: recommended
Requires-Dist: wasmtime; extra == 'recommended'
Provides-Extra: wasmtime
Requires-Dist: wasmtime; extra == 'wasmtime'
